Metadata-Version: 2.4
Name: jl-ecms-client
Version: 0.45.0
Summary: Mirix Client - Lightweight Python client for Mirix server
Home-page: https://github.com/Mirix-AI/MIRIX
Author: Mirix AI
Author-email: yuwang@mirix.io
License: Apache License 2.0
Project-URL: Documentation, https://docs.mirix.io
Project-URL: Website, https://mirix.io
Project-URL: Source Code, https://github.com/Mirix-AI/MIRIX
Project-URL: Bug Reports, https://github.com/Mirix-AI/MIRIX/issues
Keywords: ai,memory,agent,llm,assistant,client,api
Classifier: Development Status :: 4 - Beta
Classifier: Intended Audience :: Developers
Classifier: License :: OSI Approved :: Apache Software License
Classifier: Operating System :: OS Independent
Classifier: Programming Language :: Python :: 3
Classifier: Programming Language :: Python :: 3.10
Classifier: Programming Language :: Python :: 3.11
Classifier: Programming Language :: Python :: 3.12
Classifier: Programming Language :: Python :: 3.13
Classifier: Topic :: Scientific/Engineering :: Artificial Intelligence
Classifier: Topic :: Software Development :: Libraries :: Python Modules
Classifier: Topic :: Communications :: Chat
Requires-Python: >=3.10
License-File: LICENSE
Requires-Dist: requests>=2.31.0
Requires-Dist: pydantic>=2.0.0
Requires-Dist: pydantic-settings>=2.0.0
Requires-Dist: python-dotenv>=1.0.0
Requires-Dist: jinja2>=3.1.0
Requires-Dist: demjson3>=3.0.0
Requires-Dist: json-repair>=0.25.0
Requires-Dist: pytz>=2024.1
Requires-Dist: typing_extensions>=4.8.0
Requires-Dist: pyyaml>=6.0.0
Provides-Extra: dev
Requires-Dist: pytest>=6.0.0; extra == "dev"
Requires-Dist: pytest-asyncio; extra == "dev"
Requires-Dist: black; extra == "dev"
Requires-Dist: isort; extra == "dev"
Requires-Dist: flake8; extra == "dev"
Requires-Dist: mypy; extra == "dev"
Dynamic: author
Dynamic: author-email
Dynamic: classifier
Dynamic: description
Dynamic: description-content-type
Dynamic: home-page
Dynamic: keywords
Dynamic: license
Dynamic: license-file
Dynamic: project-url
Dynamic: provides-extra
Dynamic: requires-dist
Dynamic: requires-python
Dynamic: summary
